pfng/__init__.py
pfng/__version__.py
pfng/data_reader.py
pfng/generator.py
pfng/data/female_names.csv
pfng/data/female_surnames.csv
pfng/data/male_names.csv
pfng/data/male_surnames.csv
pfng-1.0.2.dist-info/LICENSE
pfng-1.0.2.dist-info/METADATA
pfng-1.0.2.dist-info/WHEEL
pfng-1.0.2.dist-info/top_level.txt
pfng-1.0.2.dist-info/RECORD
