Metadata-Version: 2.1
Name: pfng
Version: 1.0.2
Summary: Full name generator powered by thousands of Polish names and surnames. Both male and female full names can be generated.
Home-page: https://github.com/JakubPrz/Polish-Full-Name-Generator
Author: Jakub Przepiórka
Author-email: jakub.przepiorka.contact.me@gmail.com
License: MIT
Platform: Windows
Classifier: Development Status :: 4 - Beta
Classifier: Intended Audience :: Education
Classifier: Topic :: Utilities
Classifier: Operating System :: Microsoft :: Windows
Classifier: Programming Language :: Python :: 3.10
Requires-Python: >=3.10
License-File: LICENSE
